<?xml version="1.0" encoding="utf-8"?>
<elements>
	<info>
		<name>True Blue Mage Feats</name>
		<update version="1.0.9">
			<file name="feats.xml" url="https://raw.githubusercontent.com/w4termelon/elements_ffxiv_true_blue/main/FFXIV-TRUE-BLUE/feats.xml" />
		</update>
	</info>
    <!--Cosmic -->
    <element name="Research Journal - Cosmic Lore 1" type="Class Feature" source="The Blue Mage: True Blue Update" id="ID_FFXIV_CLASS_FEATURE_TRUE_BLUE_MAGE_RESEARCH_JOURNAL_COSMIC_1">
        <supports>Research Journal</supports>
        <requirements>ID_FFXIV_CLASS_FEATURE_TRUE_BLUE_MAGE_RESEARCH_JOURNAL</requirements>
        <sheet display="false" />
        <rules>
			<select type="Class Feature" name="Monster Mimicry - Cosmic Lore 1" supports="Monster Mimicry Cosmic" />
			<select type="Class Feature" name="Next Lore" supports="Research Journal"/>
		</rules>
    </element>
    <element name="Research Journal - Cosmic Lore 2" type="Class Feature" source="The Blue Mage: True Blue Update" id="ID_FFXIV_CLASS_FEATURE_TRUE_BLUE_MAGE_RESEARCH_JOURNAL_COSMIC_2">
        <supports>Research Journal</supports>
        <requirements>ID_FFXIV_CLASS_FEATURE_TRUE_BLUE_MAGE_RESEARCH_JOURNAL_COSMIC_1</requirements>
        <sheet display="false" />
        <rules>
			<select type="Class Feature" name="Monster Mimicry - Cosmic Lore 2" supports="Monster Mimicry Cosmic" />
			<select type="Class Feature" name="Next Lore" supports="Research Journal"/>
		</rules>
    </element>
    <element name="Research Journal - Cosmic Lore 3" type="Class Feature" source="The Blue Mage: True Blue Update" id="ID_FFXIV_CLASS_FEATURE_TRUE_BLUE_MAGE_RESEARCH_JOURNAL_COSMIC_3">
        <supports>Research Journal</supports>
        <requirements>ID_FFXIV_CLASS_FEATURE_TRUE_BLUE_MAGE_RESEARCH_JOURNAL_COSMIC_2</requirements>
        <sheet display="false" />
        <rules>
			<select type="Class Feature" name="Monster Mimicry - Cosmic Lore 3" supports="Monster Mimicry Cosmic" />
			<select type="Class Feature" name="Next Lore" supports="Research Journal"/>
		</rules>
    </element>
    <element name="Research Journal - Cosmic Lore 4" type="Class Feature" source="The Blue Mage: True Blue Update" id="ID_FFXIV_CLASS_FEATURE_TRUE_BLUE_MAGE_RESEARCH_JOURNAL_COSMIC_4">
        <supports>Research Journal</supports>
        <requirements>ID_FFXIV_CLASS_FEATURE_TRUE_BLUE_MAGE_RESEARCH_JOURNAL_COSMIC_3</requirements>
        <sheet display="false" />
        <rules>
			<select type="Class Feature" name="Monster Mimicry - Cosmic Lore 4" supports="Monster Mimicry Cosmic" />
			<select type="Class Feature" name="Next Lore" supports="Research Journal"/>
		</rules>
    </element>
    <element name="Research Journal - Cosmic Lore 5" type="Class Feature" source="The Blue Mage: True Blue Update" id="ID_FFXIV_CLASS_FEATURE_TRUE_BLUE_MAGE_RESEARCH_JOURNAL_COSMIC_5">
        <supports>Research Journal</supports>
        <requirements>ID_FFXIV_CLASS_FEATURE_TRUE_BLUE_MAGE_RESEARCH_JOURNAL_COSMIC_4</requirements>
        <sheet display="false" />
        <rules>
			<select type="Class Feature" name="Monster Mimicry - Cosmic Lore 5" supports="Monster Mimicry Cosmic" />
			<select type="Class Feature" name="Next Lore" supports="Research Journal"/>
		</rules>
    </element>
    <element name="Research Journal - Cosmic Lore 6" type="Class Feature" source="The Blue Mage: True Blue Update" id="ID_FFXIV_CLASS_FEATURE_TRUE_BLUE_MAGE_RESEARCH_JOURNAL_COSMIC_6">
        <supports>Research Journal</supports>
        <requirements>ID_FFXIV_CLASS_FEATURE_TRUE_BLUE_MAGE_RESEARCH_JOURNAL_COSMIC_5</requirements>
        <sheet display="false" />
        <rules>
			<select type="Class Feature" name="Monster Mimicry - Cosmic Lore 6" supports="Monster Mimicry Cosmic" />
			<select type="Class Feature" name="Next Lore" supports="Research Journal"/>
		</rules>
    </element>
    <element name="Research Journal - Cosmic Lore 7" type="Class Feature" source="The Blue Mage: True Blue Update" id="ID_FFXIV_CLASS_FEATURE_TRUE_BLUE_MAGE_RESEARCH_JOURNAL_COSMIC_7">
        <supports>Research Journal</supports>
        <requirements>ID_FFXIV_CLASS_FEATURE_TRUE_BLUE_MAGE_RESEARCH_JOURNAL_COSMIC_6</requirements>
        <sheet display="false" />
        <rules>
			<select type="Class Feature" name="Monster Mimicry - Cosmic Lore 7" supports="Monster Mimicry Cosmic" />
			<select type="Class Feature" name="Next Lore" supports="Research Journal"/>
		</rules>
    </element>
    <element name="Research Journal - Cosmic Lore 8" type="Class Feature" source="The Blue Mage: True Blue Update" id="ID_FFXIV_CLASS_FEATURE_TRUE_BLUE_MAGE_RESEARCH_JOURNAL_COSMIC_8">
        <supports>Research Journal</supports>
        <requirements>ID_FFXIV_CLASS_FEATURE_TRUE_BLUE_MAGE_RESEARCH_JOURNAL_COSMIC_7</requirements>
        <sheet display="false" />
        <rules>
			<select type="Class Feature" name="Monster Mimicry - Cosmic Lore 8" supports="Monster Mimicry Cosmic" />
			<select type="Class Feature" name="Next Lore" supports="Research Journal"/>
		</rules>
    </element>    
    <element name="Research Journal - Cosmic Lore 9" type="Class Feature" source="The Blue Mage: True Blue Update" id="ID_FFXIV_CLASS_FEATURE_TRUE_BLUE_MAGE_RESEARCH_JOURNAL_COSMIC_9">
        <supports>Research Journal</supports>
        <requirements>ID_FFXIV_CLASS_FEATURE_TRUE_BLUE_MAGE_RESEARCH_JOURNAL_COSMIC_8</requirements>
        <sheet display="false" />
        <rules>
			<select type="Class Feature" name="Monster Mimicry - Cosmic Lore 9" supports="Monster Mimicry Cosmic" />
			<select type="Class Feature" name="Next Lore" supports="Research Journal"/>
		</rules>
    </element>   
    <element name="Research Journal - Cosmic Lore 10" type="Class Feature" source="The Blue Mage: True Blue Update" id="ID_FFXIV_CLASS_FEATURE_TRUE_BLUE_MAGE_RESEARCH_JOURNAL_COSMIC_10">
        <supports>Research Journal</supports>
        <requirements>ID_FFXIV_CLASS_FEATURE_TRUE_BLUE_MAGE_RESEARCH_JOURNAL_COSMIC_9</requirements>
        <sheet display="false" />
        <rules>
			<select type="Class Feature" name="Monster Mimicry - Cosmic Lore 10" supports="Monster Mimicry Cosmic" />
			<select type="Class Feature" name="Next Lore" supports="Research Journal"/>
		</rules>
    </element>
    <!--Ancestral-->
    <element name="Research Journal - Ancestral Lore 1" type="Class Feature" source="The Blue Mage: True Blue Update" id="ID_FFXIV_CLASS_FEATURE_TRUE_BLUE_MAGE_RESEARCH_JOURNAL_ANCESTRAL_1">
        <supports>Research Journal</supports>
        <requirements>ID_FFXIV_CLASS_FEATURE_TRUE_BLUE_MAGE_RESEARCH_JOURNAL</requirements>
        <sheet display="false" />
        <rules>
			<select type="Class Feature" name="Monster Mimicry - Ancestral Lore 1" supports="Monster Mimicry Ancestral" />
			<select type="Class Feature" name="Next Lore" supports="Research Journal"/>
		</rules>
    </element>
    <element name="Research Journal - Ancestral Lore 2" type="Class Feature" source="The Blue Mage: True Blue Update" id="ID_FFXIV_CLASS_FEATURE_TRUE_BLUE_MAGE_RESEARCH_JOURNAL_ANCESTRAL_2">
        <supports>Research Journal</supports>
        <requirements>ID_FFXIV_CLASS_FEATURE_TRUE_BLUE_MAGE_RESEARCH_JOURNAL_ANCESTRAL_1</requirements>
        <sheet display="false" />
        <rules>
			<select type="Class Feature" name="Monster Mimicry - Ancestral Lore 2" supports="Monster Mimicry Ancestral" />
			<select type="Class Feature" name="Next Lore" supports="Research Journal"/>
		</rules>
    </element>
    <element name="Research Journal - Ancestral Lore 3" type="Class Feature" source="The Blue Mage: True Blue Update" id="ID_FFXIV_CLASS_FEATURE_TRUE_BLUE_MAGE_RESEARCH_JOURNAL_ANCESTRAL_3">
        <supports>Research Journal</supports>
        <requirements>ID_FFXIV_CLASS_FEATURE_TRUE_BLUE_MAGE_RESEARCH_JOURNAL_ANCESTRAL_2</requirements>
        <sheet display="false" />
        <rules>
			<select type="Class Feature" name="Monster Mimicry - Ancestral Lore 3" supports="Monster Mimicry Ancestral" />
			<select type="Class Feature" name="Next Lore" supports="Research Journal"/>
		</rules>
    </element>
    <element name="Research Journal - Ancestral Lore 4" type="Class Feature" source="The Blue Mage: True Blue Update" id="ID_FFXIV_CLASS_FEATURE_TRUE_BLUE_MAGE_RESEARCH_JOURNAL_ANCESTRAL_4">
        <supports>Research Journal</supports>
        <requirements>ID_FFXIV_CLASS_FEATURE_TRUE_BLUE_MAGE_RESEARCH_JOURNAL_ANCESTRAL_3</requirements>
        <sheet display="false" />
        <rules>
			<select type="Class Feature" name="Monster Mimicry - Ancestral Lore 4" supports="Monster Mimicry Ancestral" />
			<select type="Class Feature" name="Next Lore" supports="Research Journal"/>
		</rules>
    </element>
    <element name="Research Journal - Ancestral Lore 5" type="Class Feature" source="The Blue Mage: True Blue Update" id="ID_FFXIV_CLASS_FEATURE_TRUE_BLUE_MAGE_RESEARCH_JOURNAL_ANCESTRAL_5">
        <supports>Research Journal</supports>
        <requirements>ID_FFXIV_CLASS_FEATURE_TRUE_BLUE_MAGE_RESEARCH_JOURNAL_ANCESTRAL_4</requirements>
        <sheet display="false" />
        <rules>
			<select type="Class Feature" name="Monster Mimicry - Ancestral Lore 5" supports="Monster Mimicry Ancestral" />
			<select type="Class Feature" name="Next Lore" supports="Research Journal"/>
		</rules>
    </element>
    <element name="Research Journal - Ancestral Lore 6" type="Class Feature" source="The Blue Mage: True Blue Update" id="ID_FFXIV_CLASS_FEATURE_TRUE_BLUE_MAGE_RESEARCH_JOURNAL_ANCESTRAL_6">
        <supports>Research Journal</supports>
        <requirements>ID_FFXIV_CLASS_FEATURE_TRUE_BLUE_MAGE_RESEARCH_JOURNAL_ANCESTRAL_5</requirements>
        <sheet display="false" />
        <rules>
			<select type="Class Feature" name="Monster Mimicry - Ancestral Lore 6" supports="Monster Mimicry Ancestral" />
			<select type="Class Feature" name="Next Lore" supports="Research Journal"/>
		</rules>
    </element>
    <element name="Research Journal - Ancestral Lore 7" type="Class Feature" source="The Blue Mage: True Blue Update" id="ID_FFXIV_CLASS_FEATURE_TRUE_BLUE_MAGE_RESEARCH_JOURNAL_ANCESTRAL_7">
        <supports>Research Journal</supports>
        <requirements>ID_FFXIV_CLASS_FEATURE_TRUE_BLUE_MAGE_RESEARCH_JOURNAL_ANCESTRAL_6</requirements>
        <sheet display="false" />
        <rules>
			<select type="Class Feature" name="Monster Mimicry - Ancestral Lore 7" supports="Monster Mimicry Ancestral" />
			<select type="Class Feature" name="Next Lore" supports="Research Journal"/>
		</rules>
    </element>
    <element name="Research Journal - Ancestral Lore 8" type="Class Feature" source="The Blue Mage: True Blue Update" id="ID_FFXIV_CLASS_FEATURE_TRUE_BLUE_MAGE_RESEARCH_JOURNAL_ANCESTRAL_8">
        <supports>Research Journal</supports>
        <requirements>ID_FFXIV_CLASS_FEATURE_TRUE_BLUE_MAGE_RESEARCH_JOURNAL_ANCESTRAL_7</requirements>
        <sheet display="false" />
        <rules>
			<select type="Class Feature" name="Monster Mimicry - Ancestral Lore 8" supports="Monster Mimicry Ancestral" />
			<select type="Class Feature" name="Next Lore" supports="Research Journal"/>
		</rules>
    </element>    
    <element name="Research Journal - Ancestral Lore 9" type="Class Feature" source="The Blue Mage: True Blue Update" id="ID_FFXIV_CLASS_FEATURE_TRUE_BLUE_MAGE_RESEARCH_JOURNAL_ANCESTRAL_9">
        <supports>Research Journal</supports>
        <requirements>ID_FFXIV_CLASS_FEATURE_TRUE_BLUE_MAGE_RESEARCH_JOURNAL_ANCESTRAL_8</requirements>
        <sheet display="false" />
        <rules>
			<select type="Class Feature" name="Monster Mimicry - Ancestral Lore 9" supports="Monster Mimicry Ancestral" />
			<select type="Class Feature" name="Next Lore" supports="Research Journal"/>
		</rules>
    </element>   
    <element name="Research Journal - Ancestral Lore 10" type="Class Feature" source="The Blue Mage: True Blue Update" id="ID_FFXIV_CLASS_FEATURE_TRUE_BLUE_MAGE_RESEARCH_JOURNAL_ANCESTRAL_10">
        <supports>Research Journal</supports>
        <requirements>ID_FFXIV_CLASS_FEATURE_TRUE_BLUE_MAGE_RESEARCH_JOURNAL_ANCESTRAL_9</requirements>
        <sheet display="false" />
        <rules>
			<select type="Class Feature" name="Monster Mimicry - Ancestral Lore 10" supports="Monster Mimicry Ancestral" />
			<select type="Class Feature" name="Next Lore" supports="Research Journal"/>
		</rules>
    </element>
    <!--Primordial-->
    <element name="Research Journal - Primordial Lore 1" type="Class Feature" source="The Blue Mage: True Blue Update" id="ID_FFXIV_CLASS_FEATURE_TRUE_BLUE_MAGE_RESEARCH_JOURNAL_PRIMORDIAL_1">
        <supports>Research Journal</supports>
        <requirements>ID_FFXIV_CLASS_FEATURE_TRUE_BLUE_MAGE_RESEARCH_JOURNAL</requirements>
        <sheet display="false" />
        <rules>
			<select type="Class Feature" name="Monster Mimicry - Primordial Lore 1" supports="Monster Mimicry Primordial" />
			<select type="Class Feature" name="Next Lore" supports="Research Journal"/>
		</rules>
    </element>
    <element name="Research Journal - Primordial Lore 2" type="Class Feature" source="The Blue Mage: True Blue Update" id="ID_FFXIV_CLASS_FEATURE_TRUE_BLUE_MAGE_RESEARCH_JOURNAL_PRIMORDIAL_2">
        <supports>Research Journal</supports>
        <requirements>ID_FFXIV_CLASS_FEATURE_TRUE_BLUE_MAGE_RESEARCH_JOURNAL_PRIMORDIAL_1</requirements>
        <sheet display="false" />
        <rules>
			<select type="Class Feature" name="Monster Mimicry - Primordial Lore 2" supports="Monster Mimicry Primordial" />
			<select type="Class Feature" name="Next Lore" supports="Research Journal"/>
		</rules>
    </element>
    <element name="Research Journal - Primordial Lore 3" type="Class Feature" source="The Blue Mage: True Blue Update" id="ID_FFXIV_CLASS_FEATURE_TRUE_BLUE_MAGE_RESEARCH_JOURNAL_PRIMORDIAL_3">
        <supports>Research Journal</supports>
        <requirements>ID_FFXIV_CLASS_FEATURE_TRUE_BLUE_MAGE_RESEARCH_JOURNAL_PRIMORDIAL_2</requirements>
        <sheet display="false" />
        <rules>
			<select type="Class Feature" name="Monster Mimicry - Primordial Lore 3" supports="Monster Mimicry Primordial" />
			<select type="Class Feature" name="Next Lore" supports="Research Journal"/>
		</rules>
    </element>
    <element name="Research Journal - Primordial Lore 4" type="Class Feature" source="The Blue Mage: True Blue Update" id="ID_FFXIV_CLASS_FEATURE_TRUE_BLUE_MAGE_RESEARCH_JOURNAL_PRIMORDIAL_4">
        <supports>Research Journal</supports>
        <requirements>ID_FFXIV_CLASS_FEATURE_TRUE_BLUE_MAGE_RESEARCH_JOURNAL_PRIMORDIAL_3</requirements>
        <sheet display="false" />
        <rules>
			<select type="Class Feature" name="Monster Mimicry - Primordial Lore 4" supports="Monster Mimicry Primordial" />
			<select type="Class Feature" name="Next Lore" supports="Research Journal"/>
		</rules>
    </element>
    <element name="Research Journal - Primordial Lore 5" type="Class Feature" source="The Blue Mage: True Blue Update" id="ID_FFXIV_CLASS_FEATURE_TRUE_BLUE_MAGE_RESEARCH_JOURNAL_PRIMORDIAL_5">
        <supports>Research Journal</supports>
        <requirements>ID_FFXIV_CLASS_FEATURE_TRUE_BLUE_MAGE_RESEARCH_JOURNAL_PRIMORDIAL_4</requirements>
        <sheet display="false" />
        <rules>
			<select type="Class Feature" name="Monster Mimicry - Primordial Lore 5" supports="Monster Mimicry Primordial" />
			<select type="Class Feature" name="Next Lore" supports="Research Journal"/>
		</rules>
    </element>
    <element name="Research Journal - Primordial Lore 6" type="Class Feature" source="The Blue Mage: True Blue Update" id="ID_FFXIV_CLASS_FEATURE_TRUE_BLUE_MAGE_RESEARCH_JOURNAL_PRIMORDIAL_6">
        <supports>Research Journal</supports>
        <requirements>ID_FFXIV_CLASS_FEATURE_TRUE_BLUE_MAGE_RESEARCH_JOURNAL_PRIMORDIAL_5</requirements>
        <sheet display="false" />
        <rules>
			<select type="Class Feature" name="Monster Mimicry - Primordial Lore 6" supports="Monster Mimicry Primordial" />
			<select type="Class Feature" name="Next Lore" supports="Research Journal"/>
		</rules>
    </element>
    <element name="Research Journal - Primordial Lore 7" type="Class Feature" source="The Blue Mage: True Blue Update" id="ID_FFXIV_CLASS_FEATURE_TRUE_BLUE_MAGE_RESEARCH_JOURNAL_PRIMORDIAL_7">
        <supports>Research Journal</supports>
        <requirements>ID_FFXIV_CLASS_FEATURE_TRUE_BLUE_MAGE_RESEARCH_JOURNAL_PRIMORDIAL_6</requirements>
        <sheet display="false" />
        <rules>
			<select type="Class Feature" name="Monster Mimicry - Primordial Lore 7" supports="Monster Mimicry Primordial" />
			<select type="Class Feature" name="Next Lore" supports="Research Journal"/>
		</rules>
    </element>
    <element name="Research Journal - Primordial Lore 8" type="Class Feature" source="The Blue Mage: True Blue Update" id="ID_FFXIV_CLASS_FEATURE_TRUE_BLUE_MAGE_RESEARCH_JOURNAL_PRIMORDIAL_8">
        <supports>Research Journal</supports>
        <requirements>ID_FFXIV_CLASS_FEATURE_TRUE_BLUE_MAGE_RESEARCH_JOURNAL_PRIMORDIAL_7</requirements>
        <sheet display="false" />
        <rules>
			<select type="Class Feature" name="Monster Mimicry - Primordial Lore 8" supports="Monster Mimicry Primordial" />
			<select type="Class Feature" name="Next Lore" supports="Research Journal"/>
		</rules>
    </element>    
    <element name="Research Journal - Primordial Lore 9" type="Class Feature" source="The Blue Mage: True Blue Update" id="ID_FFXIV_CLASS_FEATURE_TRUE_BLUE_MAGE_RESEARCH_JOURNAL_PRIMORDIAL_9">
        <supports>Research Journal</supports>
        <requirements>ID_FFXIV_CLASS_FEATURE_TRUE_BLUE_MAGE_RESEARCH_JOURNAL_PRIMORDIAL_8</requirements>
        <sheet display="false" />
        <rules>
			<select type="Class Feature" name="Monster Mimicry - Primordial Lore 9" supports="Monster Mimicry Primordial" />
			<select type="Class Feature" name="Next Lore" supports="Research Journal"/>
		</rules>
    </element>   
    <element name="Research Journal - Primordial Lore 10" type="Class Feature" source="The Blue Mage: True Blue Update" id="ID_FFXIV_CLASS_FEATURE_TRUE_BLUE_MAGE_RESEARCH_JOURNAL_PRIMORDIAL_10">
        <supports>Research Journal</supports>
        <requirements>ID_FFXIV_CLASS_FEATURE_TRUE_BLUE_MAGE_RESEARCH_JOURNAL_PRIMORDIAL_9</requirements>
        <sheet display="false" />
        <rules>
			<select type="Class Feature" name="Monster Mimicry - Primordial Lore 10" supports="Monster Mimicry Primordial" />
			<select type="Class Feature" name="Next Lore" supports="Research Journal"/>
		</rules>
    </element>
    <!--Sacred-->
    <element name="Research Journal - Sacred Lore 1" type="Class Feature" source="The Blue Mage: True Blue Update" id="ID_FFXIV_CLASS_FEATURE_TRUE_BLUE_MAGE_RESEARCH_JOURNAL_SACRED_1">
        <supports>Research Journal</supports>
        <requirements>ID_FFXIV_CLASS_FEATURE_TRUE_BLUE_MAGE_RESEARCH_JOURNAL</requirements>
        <sheet display="false" />
        <rules>
			<select type="Class Feature" name="Monster Mimicry - Sacred Lore 1" supports="Monster Mimicry Sacred" />
			<select type="Class Feature" name="Next Lore" supports="Research Journal"/>
		</rules>
    </element>
    <element name="Research Journal - Sacred Lore 2" type="Class Feature" source="The Blue Mage: True Blue Update" id="ID_FFXIV_CLASS_FEATURE_TRUE_BLUE_MAGE_RESEARCH_JOURNAL_SACRED_2">
        <supports>Research Journal</supports>
        <requirements>ID_FFXIV_CLASS_FEATURE_TRUE_BLUE_MAGE_RESEARCH_JOURNAL_SACRED_1</requirements>
        <sheet display="false" />
        <rules>
			<select type="Class Feature" name="Monster Mimicry - Sacred Lore 2" supports="Monster Mimicry Sacred" />
			<select type="Class Feature" name="Next Lore" supports="Research Journal"/>
		</rules>
    </element>
    <element name="Research Journal - Sacred Lore 3" type="Class Feature" source="The Blue Mage: True Blue Update" id="ID_FFXIV_CLASS_FEATURE_TRUE_BLUE_MAGE_RESEARCH_JOURNAL_SACRED_3">
        <supports>Research Journal</supports>
        <requirements>ID_FFXIV_CLASS_FEATURE_TRUE_BLUE_MAGE_RESEARCH_JOURNAL_SACRED_2</requirements>
        <sheet display="false" />
        <rules>
			<select type="Class Feature" name="Monster Mimicry - Sacred Lore 3" supports="Monster Mimicry Sacred" />
			<select type="Class Feature" name="Next Lore" supports="Research Journal"/>
		</rules>
    </element>
    <element name="Research Journal - Sacred Lore 4" type="Class Feature" source="The Blue Mage: True Blue Update" id="ID_FFXIV_CLASS_FEATURE_TRUE_BLUE_MAGE_RESEARCH_JOURNAL_SACRED_4">
        <supports>Research Journal</supports>
        <requirements>ID_FFXIV_CLASS_FEATURE_TRUE_BLUE_MAGE_RESEARCH_JOURNAL_SACRED_3</requirements>
        <sheet display="false" />
        <rules>
			<select type="Class Feature" name="Monster Mimicry - Sacred Lore 4" supports="Monster Mimicry Sacred" />
			<select type="Class Feature" name="Next Lore" supports="Research Journal"/>
		</rules>
    </element>
    <element name="Research Journal - Sacred Lore 5" type="Class Feature" source="The Blue Mage: True Blue Update" id="ID_FFXIV_CLASS_FEATURE_TRUE_BLUE_MAGE_RESEARCH_JOURNAL_SACRED_5">
        <supports>Research Journal</supports>
        <requirements>ID_FFXIV_CLASS_FEATURE_TRUE_BLUE_MAGE_RESEARCH_JOURNAL_SACRED_4</requirements>
        <sheet display="false" />
        <rules>
			<select type="Class Feature" name="Monster Mimicry - Sacred Lore 5" supports="Monster Mimicry Sacred" />
			<select type="Class Feature" name="Next Lore" supports="Research Journal"/>
		</rules>
    </element>
    <element name="Research Journal - Sacred Lore 6" type="Class Feature" source="The Blue Mage: True Blue Update" id="ID_FFXIV_CLASS_FEATURE_TRUE_BLUE_MAGE_RESEARCH_JOURNAL_SACRED_6">
        <supports>Research Journal</supports>
        <requirements>ID_FFXIV_CLASS_FEATURE_TRUE_BLUE_MAGE_RESEARCH_JOURNAL_SACRED_5</requirements>
        <sheet display="false" />
        <rules>
			<select type="Class Feature" name="Monster Mimicry - Sacred Lore 6" supports="Monster Mimicry Sacred" />
			<select type="Class Feature" name="Next Lore" supports="Research Journal"/>
		</rules>
    </element>
    <element name="Research Journal - Sacred Lore 7" type="Class Feature" source="The Blue Mage: True Blue Update" id="ID_FFXIV_CLASS_FEATURE_TRUE_BLUE_MAGE_RESEARCH_JOURNAL_SACRED_7">
        <supports>Research Journal</supports>
        <requirements>ID_FFXIV_CLASS_FEATURE_TRUE_BLUE_MAGE_RESEARCH_JOURNAL_SACRED_6</requirements>
        <sheet display="false" />
        <rules>
			<select type="Class Feature" name="Monster Mimicry - Sacred Lore 7" supports="Monster Mimicry Sacred" />
			<select type="Class Feature" name="Next Lore" supports="Research Journal"/>
		</rules>
    </element>
    <element name="Research Journal - Sacred Lore 8" type="Class Feature" source="The Blue Mage: True Blue Update" id="ID_FFXIV_CLASS_FEATURE_TRUE_BLUE_MAGE_RESEARCH_JOURNAL_SACRED_8">
        <supports>Research Journal</supports>
        <requirements>ID_FFXIV_CLASS_FEATURE_TRUE_BLUE_MAGE_RESEARCH_JOURNAL_SACRED_7</requirements>
        <sheet display="false" />
        <rules>
			<select type="Class Feature" name="Monster Mimicry - Sacred Lore 8" supports="Monster Mimicry Sacred" />
			<select type="Class Feature" name="Next Lore" supports="Research Journal"/>
		</rules>
    </element>    
    <element name="Research Journal - Sacred Lore 9" type="Class Feature" source="The Blue Mage: True Blue Update" id="ID_FFXIV_CLASS_FEATURE_TRUE_BLUE_MAGE_RESEARCH_JOURNAL_SACRED_9">
        <supports>Research Journal</supports>
        <requirements>ID_FFXIV_CLASS_FEATURE_TRUE_BLUE_MAGE_RESEARCH_JOURNAL_SACRED_8</requirements>
        <sheet display="false" />
        <rules>
			<select type="Class Feature" name="Monster Mimicry - Sacred Lore 9" supports="Monster Mimicry Sacred" />
			<select type="Class Feature" name="Next Lore" supports="Research Journal"/>
		</rules>
    </element>   
    <element name="Research Journal - Sacred Lore 10" type="Class Feature" source="The Blue Mage: True Blue Update" id="ID_FFXIV_CLASS_FEATURE_TRUE_BLUE_MAGE_RESEARCH_JOURNAL_SACRED_10">
        <supports>Research Journal</supports>
        <requirements>ID_FFXIV_CLASS_FEATURE_TRUE_BLUE_MAGE_RESEARCH_JOURNAL_SACRED_9</requirements>
        <sheet display="false" />
        <rules>
			<select type="Class Feature" name="Monster Mimicry - Sacred Lore 10" supports="Monster Mimicry Sacred" />
			<select type="Class Feature" name="Next Lore" supports="Research Journal"/>
		</rules>
    </element>
    <!--Supernatural-->
    <element name="Research Journal - Supernatural Lore 1" type="Class Feature" source="The Blue Mage: True Blue Update" id="ID_FFXIV_CLASS_FEATURE_TRUE_BLUE_MAGE_RESEARCH_JOURNAL_SUPERNATURAL_1">
        <supports>Research Journal</supports>
        <requirements>ID_FFXIV_CLASS_FEATURE_TRUE_BLUE_MAGE_RESEARCH_JOURNAL</requirements>
        <sheet display="false" />
        <rules>
			<select type="Class Feature" name="Monster Mimicry - Supernatural Lore 1" supports="Monster Mimicry Supernatural" />
			<select type="Class Feature" name="Next Lore" supports="Research Journal"/>
		</rules>
    </element>
    <element name="Research Journal - Supernatural Lore 2" type="Class Feature" source="The Blue Mage: True Blue Update" id="ID_FFXIV_CLASS_FEATURE_TRUE_BLUE_MAGE_RESEARCH_JOURNAL_SUPERNATURAL_2">
        <supports>Research Journal</supports>
        <requirements>ID_FFXIV_CLASS_FEATURE_TRUE_BLUE_MAGE_RESEARCH_JOURNAL_SUPERNATURAL_1</requirements>
        <sheet display="false" />
        <rules>
			<select type="Class Feature" name="Monster Mimicry - Supernatural Lore 2" supports="Monster Mimicry Supernatural" />
			<select type="Class Feature" name="Next Lore" supports="Research Journal"/>
		</rules>
    </element>
    <element name="Research Journal - Supernatural Lore 3" type="Class Feature" source="The Blue Mage: True Blue Update" id="ID_FFXIV_CLASS_FEATURE_TRUE_BLUE_MAGE_RESEARCH_JOURNAL_SUPERNATURAL_3">
        <requirements>ID_FFXIV_CLASS_FEATURE_TRUE_BLUE_MAGE_RESEARCH_JOURNAL_SUPERNATURAL_2</requirements>
        <sheet display="false" />
        <rules>
			<select type="Class Feature" name="Monster Mimicry - Supernatural Lore 3" supports="Monster Mimicry Supernatural" />
			<select type="Class Feature" name="Next Lore" supports="Research Journal"/>
		</rules>
    </element>
    <element name="Research Journal - Supernatural Lore 4" type="Class Feature" source="The Blue Mage: True Blue Update" id="ID_FFXIV_CLASS_FEATURE_TRUE_BLUE_MAGE_RESEARCH_JOURNAL_SUPERNATURAL_4">
        <supports>Research Journal</supports>
        <requirements>ID_FFXIV_CLASS_FEATURE_TRUE_BLUE_MAGE_RESEARCH_JOURNAL_SUPERNATURAL_3</requirements>
        <sheet display="false" />
        <rules>
			<select type="Class Feature" name="Monster Mimicry - Supernatural Lore 4" supports="Monster Mimicry Supernatural" />
			<select type="Class Feature" name="Next Lore" supports="Research Journal"/>
		</rules>
    </element>
    <element name="Research Journal - Supernatural Lore 5" type="Class Feature" source="The Blue Mage: True Blue Update" id="ID_FFXIV_CLASS_FEATURE_TRUE_BLUE_MAGE_RESEARCH_JOURNAL_SUPERNATURAL_5">
        <supports>Research Journal</supports>
        <requirements>ID_FFXIV_CLASS_FEATURE_TRUE_BLUE_MAGE_RESEARCH_JOURNAL_SUPERNATURAL_4</requirements>
        <sheet display="false" />
        <rules>
			<select type="Class Feature" name="Monster Mimicry - Supernatural Lore 5" supports="Monster Mimicry Supernatural" />
			<select type="Class Feature" name="Next Lore" supports="Research Journal"/>
		</rules>
    </element>
    <element name="Research Journal - Supernatural Lore 6" type="Class Feature" source="The Blue Mage: True Blue Update" id="ID_FFXIV_CLASS_FEATURE_TRUE_BLUE_MAGE_RESEARCH_JOURNAL_SUPERNATURAL_6">
        <supports>Research Journal</supports>
        <requirements>ID_FFXIV_CLASS_FEATURE_TRUE_BLUE_MAGE_RESEARCH_JOURNAL_SUPERNATURAL_5</requirements>
        <sheet display="false" />
        <rules>
			<select type="Class Feature" name="Monster Mimicry - Supernatural Lore 6" supports="Monster Mimicry Supernatural" />
			<select type="Class Feature" name="Next Lore" supports="Research Journal"/>
		</rules>
    </element>
    <element name="Research Journal - Supernatural Lore 7" type="Class Feature" source="The Blue Mage: True Blue Update" id="ID_FFXIV_CLASS_FEATURE_TRUE_BLUE_MAGE_RESEARCH_JOURNAL_SUPERNATURAL_7">
        <supports>Research Journal</supports>
        <requirements>ID_FFXIV_CLASS_FEATURE_TRUE_BLUE_MAGE_RESEARCH_JOURNAL_SUPERNATURAL_6</requirements>
        <sheet display="false" />
        <rules>
			<select type="Class Feature" name="Monster Mimicry - Supernatural Lore 7" supports="Monster Mimicry Supernatural" />
			<select type="Class Feature" name="Next Lore" supports="Research Journal"/>
		</rules>
    </element>
    <element name="Research Journal - Supernatural Lore 8" type="Class Feature" source="The Blue Mage: True Blue Update" id="ID_FFXIV_CLASS_FEATURE_TRUE_BLUE_MAGE_RESEARCH_JOURNAL_SUPERNATURAL_8">
        <supports>Research Journal</supports>
        <requirements>ID_FFXIV_CLASS_FEATURE_TRUE_BLUE_MAGE_RESEARCH_JOURNAL_SUPERNATURAL_7</requirements>
        <sheet display="false" />
        <rules>
			<select type="Class Feature" name="Monster Mimicry - Supernatural Lore 8" supports="Monster Mimicry Supernatural" />
			<select type="Class Feature" name="Next Lore" supports="Research Journal"/>
		</rules>
    </element>    
    <element name="Research Journal - Supernatural Lore 9" type="Class Feature" source="The Blue Mage: True Blue Update" id="ID_FFXIV_CLASS_FEATURE_TRUE_BLUE_MAGE_RESEARCH_JOURNAL_SUPERNATURAL_9">
        <supports>Research Journal</supports>
        <requirements>ID_FFXIV_CLASS_FEATURE_TRUE_BLUE_MAGE_RESEARCH_JOURNAL_SUPERNATURAL_8</requirements>
        <sheet display="false" />
        <rules>
			<select type="Class Feature" name="Monster Mimicry - Supernatural Lore 9" supports="Monster Mimicry Supernatural" />
			<select type="Class Feature" name="Next Lore" supports="Research Journal"/>
		</rules>
    </element>   
    <element name="Research Journal - Supernatural Lore 10" type="Class Feature" source="The Blue Mage: True Blue Update" id="ID_FFXIV_CLASS_FEATURE_TRUE_BLUE_MAGE_RESEARCH_JOURNAL_SUPERNATURAL_10">
        <supports>Research Journal</supports>
        <requirements>ID_FFXIV_CLASS_FEATURE_TRUE_BLUE_MAGE_RESEARCH_JOURNAL_SUPERNATURAL_9</requirements>
        <sheet display="false" />
        <rules>
			<select type="Class Feature" name="Monster Mimicry - Supernatural Lore 10" supports="Monster Mimicry Supernatural" />
			<select type="Class Feature" name="Next Lore" supports="Research Journal"/>
		</rules>
    </element>
    <!--Mythical-->
    <element name="Research Journal - Mythical Lore 1" type="Class Feature" source="The Blue Mage: True Blue Update" id="ID_FFXIV_CLASS_FEATURE_TRUE_BLUE_MAGE_RESEARCH_JOURNAL_MYTHICAL_1">
        <supports>Research Journal</supports>
        <requirements>ID_FFXIV_CLASS_FEATURE_TRUE_BLUE_MAGE_RESEARCH_JOURNAL</requirements>
        <sheet display="false" />
        <rules>
			<select type="Class Feature" name="Monster Mimicry - Mythical Lore 1" supports="Monster Mimicry Mythical" />
			<select type="Class Feature" name="Next Lore" supports="Research Journal"/>
		</rules>
    </element>
    <element name="Research Journal - Mythical Lore 2" type="Class Feature" source="The Blue Mage: True Blue Update" id="ID_FFXIV_CLASS_FEATURE_TRUE_BLUE_MAGE_RESEARCH_JOURNAL_MYTHICAL_2">
        <supports>Research Journal</supports>
        <requirements>ID_FFXIV_CLASS_FEATURE_TRUE_BLUE_MAGE_RESEARCH_JOURNAL_MYTHICAL_1</requirements>
        <sheet display="false" />
        <rules>
			<select type="Class Feature" name="Monster Mimicry - Mythical Lore 2" supports="Monster Mimicry Mythical" />
			<select type="Class Feature" name="Next Lore" supports="Research Journal"/>
		</rules>
    </element>
    <element name="Research Journal - Mythical Lore 3" type="Class Feature" source="The Blue Mage: True Blue Update" id="ID_FFXIV_CLASS_FEATURE_TRUE_BLUE_MAGE_RESEARCH_JOURNAL_MYTHICAL_3">
        <supports>Research Journal</supports>
        <requirements>ID_FFXIV_CLASS_FEATURE_TRUE_BLUE_MAGE_RESEARCH_JOURNAL_MYTHICAL_2</requirements>
        <sheet display="false" />
        <rules>
			<select type="Class Feature" name="Monster Mimicry - Mythical Lore 3" supports="Monster Mimicry Mythical" />
			<select type="Class Feature" name="Next Lore" supports="Research Journal"/>
		</rules>
    </element>
    <element name="Research Journal - Mythical Lore 4" type="Class Feature" source="The Blue Mage: True Blue Update" id="ID_FFXIV_CLASS_FEATURE_TRUE_BLUE_MAGE_RESEARCH_JOURNAL_MYTHICAL_4">
        <supports>Research Journal</supports>
        <requirements>ID_FFXIV_CLASS_FEATURE_TRUE_BLUE_MAGE_RESEARCH_JOURNAL_MYTHICAL_3</requirements>
        <sheet display="false" />
        <rules>
			<select type="Class Feature" name="Monster Mimicry - Mythical Lore 4" supports="Monster Mimicry Mythical" />
			<select type="Class Feature" name="Next Lore" supports="Research Journal"/>
		</rules>
    </element>
    <element name="Research Journal - Mythical Lore 5" type="Class Feature" source="The Blue Mage: True Blue Update" id="ID_FFXIV_CLASS_FEATURE_TRUE_BLUE_MAGE_RESEARCH_JOURNAL_MYTHICAL_5">
        <supports>Research Journal</supports>
        <requirements>ID_FFXIV_CLASS_FEATURE_TRUE_BLUE_MAGE_RESEARCH_JOURNAL_MYTHICAL_4</requirements>
        <sheet display="false" />
        <rules>
			<select type="Class Feature" name="Monster Mimicry - Mythical Lore 5" supports="Monster Mimicry Mythical" />
			<select type="Class Feature" name="Next Lore" supports="Research Journal"/>
		</rules>
    </element>
    <element name="Research Journal - Mythical Lore 6" type="Class Feature" source="The Blue Mage: True Blue Update" id="ID_FFXIV_CLASS_FEATURE_TRUE_BLUE_MAGE_RESEARCH_JOURNAL_MYTHICAL_6">
        <supports>Research Journal</supports>
        <requirements>ID_FFXIV_CLASS_FEATURE_TRUE_BLUE_MAGE_RESEARCH_JOURNAL_MYTHICAL_5</requirements>
        <sheet display="false" />
        <rules>
			<select type="Class Feature" name="Monster Mimicry - Mythical Lore 6" supports="Monster Mimicry Mythical" />
			<select type="Class Feature" name="Next Lore" supports="Research Journal"/>
		</rules>
    </element>
    <element name="Research Journal - Mythical Lore 7" type="Class Feature" source="The Blue Mage: True Blue Update" id="ID_FFXIV_CLASS_FEATURE_TRUE_BLUE_MAGE_RESEARCH_JOURNAL_MYTHICAL_7">
        <supports>Research Journal</supports>
        <requirements>ID_FFXIV_CLASS_FEATURE_TRUE_BLUE_MAGE_RESEARCH_JOURNAL_MYTHICAL_6</requirements>
        <sheet display="false" />
        <rules>
			<select type="Class Feature" name="Monster Mimicry - Mythical Lore 7" supports="Monster Mimicry Mythical" />
			<select type="Class Feature" name="Next Lore" supports="Research Journal"/>
		</rules>
    </element>
    <element name="Research Journal - Mythical Lore 8" type="Class Feature" source="The Blue Mage: True Blue Update" id="ID_FFXIV_CLASS_FEATURE_TRUE_BLUE_MAGE_RESEARCH_JOURNAL_MYTHICAL_8">
        <supports>Research Journal</supports>
        <requirements>ID_FFXIV_CLASS_FEATURE_TRUE_BLUE_MAGE_RESEARCH_JOURNAL_MYTHICAL_7</requirements>
        <sheet display="false" />
        <rules>
			<select type="Class Feature" name="Monster Mimicry - Mythical Lore 8" supports="Monster Mimicry Mythical" />
			<select type="Class Feature" name="Next Lore" supports="Research Journal"/>
		</rules>
    </element>    
    <element name="Research Journal - Mythical Lore 9" type="Class Feature" source="The Blue Mage: True Blue Update" id="ID_FFXIV_CLASS_FEATURE_TRUE_BLUE_MAGE_RESEARCH_JOURNAL_MYTHICAL_9">
        <supports>Research Journal</supports>
        <requirements>ID_FFXIV_CLASS_FEATURE_TRUE_BLUE_MAGE_RESEARCH_JOURNAL_MYTHICAL_8</requirements>
        <sheet display="false" />
        <rules>
			<select type="Class Feature" name="Monster Mimicry - Mythical Lore 9" supports="Monster Mimicry Mythical" />
			<select type="Class Feature" name="Next Lore" supports="Research Journal"/>
		</rules>
    </element>   
    <element name="Research Journal - Mythical Lore 10" type="Class Feature" source="The Blue Mage: True Blue Update" id="ID_FFXIV_CLASS_FEATURE_TRUE_BLUE_MAGE_RESEARCH_JOURNAL_MYTHICAL_10">
        <supports>Research Journal</supports>
        <requirements>ID_FFXIV_CLASS_FEATURE_TRUE_BLUE_MAGE_RESEARCH_JOURNAL_MYTHICAL_9</requirements>
        <sheet display="false" />
        <rules>
			<select type="Class Feature" name="Monster Mimicry - Mythical Lore 10" supports="Monster Mimicry Mythical" />
			<select type="Class Feature" name="Next Lore" supports="Research Journal"/>
		</rules>
    </element>
    <!--LORE-->
    <element name="Aberrant Ground" type="Class Feature" source="The Blue Mage: True Blue Update" id="ID_FFXIV_TRUE_BLUE_MAGE_MIMICRY_ABERRANT_GROUND">
        <supports>Monster Mimicry Cosmic</supports>
        <sheet display="false" />
    </element> 
    <element name="Adhesive Appendage" type="Class Feature" source="The Blue Mage: True Blue Update" id="ID_FFXIV_TRUE_BLUE_MAGE_MIMICRY_ADHESIVE_APPENDAGE">
        <supports>Monster Mimicry Cosmic</supports>
        <sheet display="false" />
    </element>
    <element name="All-Around Vision" type="Class Feature" source="The Blue Mage: True Blue Update" id="ID_FFXIV_TRUE_BLUE_MAGE_MIMICRY_ALL_AROUND_VISION">
            <supports>Monster Mimicry Cosmic</supports>
            <sheet display="false" />
    </element>    
    <element name="King of the Puddings" type="Class Feature" source="The Blue Mage: True Blue Update" id="ID_FFXIV_TRUE_BLUE_MAGE_MIMICRY_KING_OF_THE_PUDDINGS">
            <supports>Monster Mimicry Cosmic</supports>
            <sheet display="false" />
    </element>    
    <element name="Limited Telepathy" type="Class Feature" source="The Blue Mage: True Blue Update" id="ID_FFXIV_TRUE_BLUE_MAGE_MIMICRY_LIMITED_TELEPATHY">
            <supports>Monster Mimicry Cosmic</supports>
            <sheet display="false" />
    </element>    
    <element name="Maddening Glare" type="Class Feature" source="The Blue Mage: True Blue Update" id="ID_FFXIV_TRUE_BLUE_MAGE_MIMICRY_MADDENING_GLARE">
        <supports>Monster Mimicry Cosmic</supports>
        <sheet display="false" />
    </element>
    <element name="Mind-Breaking Touch" type="Class Feature" source="The Blue Mage: True Blue Update" id="ID_FFXIV_TRUE_BLUE_MAGE_MIMICRY_MIND_BREAKING_TOUCH">
        <supports>Monster Mimicry Cosmic</supports>
        <sheet display="false" />
    </element>    
    <element name="Ooze Climb" type="Class Feature" source="The Blue Mage: True Blue Update" id="ID_FFXIV_TRUE_BLUE_MAGE_MIMICRY_OOZE_CLIMB">
        <supports>Monster Mimicry Cosmic</supports>
        <sheet display="false" />
    </element>    
    <element name="Pseudopod Appendage" type="Class Feature" source="The Blue Mage: True Blue Update" id="ID_FFXIV_TRUE_BLUE_MAGE_MIMICRY_PSEUDOPOD_APPENDAGE">
        <supports>Monster Mimicry Cosmic</supports>
        <sheet display="false" />
    </element>    
    <element name="Sensorium" type="Class Feature" source="The Blue Mage: True Blue Update" id="ID_FFXIV_TRUE_BLUE_MAGE_MIMICRY_SENSORIUM">
        <supports>Monster Mimicry Cosmic</supports>
        <sheet display="false" />
    </element>    
    <element name="Slime Breath" type="Class Feature" source="The Blue Mage: True Blue Update" id="ID_FFXIV_TRUE_BLUE_MAGE_MIMICRY_SLIME_BREATH">
        <supports>Monster Mimicry Cosmic</supports>
        <sheet display="false" />
    </element>
    <element name="Sticky Secretions" type="Class Feature" source="The Blue Mage: True Blue Update" id="ID_FFXIV_TRUE_BLUE_MAGE_MIMICRY_STICKY_SECRETIONS">
        <supports>Monster Mimicry Cosmic</supports>
        <sheet display="false" />
    </element> 
    <element name="Vomit Ooze" type="Class Feature" source="The Blue Mage: True Blue Update" id="ID_FFXIV_TRUE_BLUE_MAGE_MIMICRY_VOMIT_OOZE">
        <supports>Monster Mimicry Cosmic</supports>
        <sheet display="false" />
    </element>
    <element name="Alien Mind" type="Class Feature" source="The Blue Mage: True Blue Update" id="ID_FFXIV_TRUE_BLUE_MAGE_MIMICRY_ALIEN_MIND">
        <supports>Monster Mimicry Cosmic</supports>
        <requirements>[level:5]</requirements>
        <sheet display="false" />
    </element>    
    <element name="Caustic Expulsion" type="Class Feature" source="The Blue Mage: True Blue Update" id="ID_FFXIV_TRUE_BLUE_MAGE_MIMICRY_CAUSTIC_EXPULSION">
        <supports>Monster Mimicry Cosmic</supports>
        <requirements>[level:9]</requirements>
        <sheet display="false" />
    </element>
    <element name="Eat Memories" type="Class Feature" source="The Blue Mage: True Blue Update" id="ID_FFXIV_TRUE_BLUE_MAGE_MIMICRY_EAT_MEMORIES">
        <supports>Monster Mimicry Cosmic</supports>
        <requirements>[level:6]</requirements>
        <sheet display="false" />
    </element>
    <element name="Enslave" type="Class Feature" source="The Blue Mage: True Blue Update" id="ID_FFXIV_TRUE_BLUE_MAGE_MIMICRY_ENSLAVE">
        <supports>Monster Mimicry Cosmic</supports>
        <requirements>[level:7]</requirements>
        <sheet display="false" />
    </element>
    <element name="Exert Will" type="Class Feature" source="The Blue Mage: True Blue Update" id="ID_FFXIV_TRUE_BLUE_MAGE_MIMICRY_EXERT_WILL">
        <supports>Monster Mimicry Cosmic</supports>
        <requirements>[level:5]</requirements>
        <sheet display="false" />
    </element>
    <element name="Psionic Rally" type="Class Feature" source="The Blue Mage: True Blue Update" id="ID_FFXIV_TRUE_BLUE_MAGE_MIMICRY_PSIONIC_RALLY">
        <supports>Monster Mimicry Cosmic</supports>
        <requirements>[level:5]</requirements>
        <sheet display="false" />
    </element>    
    <element name="Psychewall" type="Class Feature" source="The Blue Mage: True Blue Update" id="ID_FFXIV_TRUE_BLUE_MAGE_MIMICRY_PSYCHEWALL">
        <supports>Monster Mimicry Cosmic</supports>
        <requirements>[level:7]</requirements>
        <sheet display="false" />
    </element>
    <element name="Psychic Backlash" type="Class Feature" source="The Blue Mage: True Blue Update" id="ID_FFXIV_TRUE_BLUE_MAGE_MIMICRY_PSYCHIC_BACKLASH">
        <supports>Monster Mimicry Cosmic</supports>
        <requirements>[level:6]</requirements>
        <sheet display="false" />
    </element>
    <element name="Telepathic Hub" type="Class Feature" source="The Blue Mage: True Blue Update" id="ID_FFXIV_TRUE_BLUE_MAGE_MIMICRY_TELEPATHIC_HUB">
        <supports>Monster Mimicry Cosmic</supports>
        <requirements>[level:5]</requirements>
        <sheet display="false" />
    </element>
    <element name="Protective Thrall" type="Class Feature" source="The Blue Mage: True Blue Update" id="ID_FFXIV_TRUE_BLUE_MAGE_MIMICRY_PROTECTIVE_THRALL">
        <supports>Monster Mimicry Cosmic</supports>
        <requirements>[level:11]</requirements>
        <sheet display="false" />
    </element>
    <!-- Mythical Lore -->
    <element name="Azure Minora" type="Class Feature" source="The Blue Mage: True Blue Update" id="ID_FFXIV_TRUE_BLUE_MAGE_MIMICRY_AZURE_MINORA">
        <supports>Monster Mimicry Mythical</supports>
        <sheet display="false" />
    </element>
    <element name="Gaze of the Warden" type="Class Feature" source="The Blue Mage: True Blue Update" id="ID_FFXIV_TRUE_BLUE_MAGE_MIMICRY_GAZE_OF_THE_WARDEN">
        <supports>Monster Mimicry Mythical</supports>
        <sheet display="false" />
    </element>
    <element name="Harrowing Glare" type="Class Feature" source="The Blue Mage: True Blue Update" id="ID_FFXIV_TRUE_BLUE_MAGE_MIMICRY_HARROWING_GLAREID_FFXIV_TRUE_BLUE_MAGE_MIMICRY_HARROWING_GLARE">
        <supports>Monster Mimicry Mythical</supports>
        <sheet display="false" />
    </element>
    <element name="Heart Sight" type="Class Feature" source="The Blue Mage: True Blue Update" id="ID_FFXIV_TRUE_BLUE_MAGE_MIMICRY_HEART_SIGHT">
        <supports>Monster Mimicry Mythical</supports>
        <sheet display="false" />
    </element>
    <element name="Illumination" type="Class Feature" source="The Blue Mage: True Blue Update" id="ID_FFXIV_TRUE_BLUE_MAGE_MIMICRY_ILLUMINATION">
        <supports>Monster Mimicry Mythical</supports>
        <sheet display="false" />
    </element>
    <element name="Inscrutable" type="Class Feature" source="The Blue Mage: True Blue Update" id="ID_FFXIV_TRUE_BLUE_MAGE_MIMICRY_INSCRUTABLE">
        <supports>Monster Mimicry Mythical</supports>
        <sheet display="false" />
    </element>
    <element name="Iron Scent" type="Class Feature" source="The Blue Mage: True Blue Update" id="ID_FFXIV_TRUE_BLUE_MAGE_MIMICRY_IRON_SCENT">
        <supports>Monster Mimicry Mythical</supports>
        <sheet display="false" />
    </element>
    <element name="Labyrinthine Recall" type="Class Feature" source="The Blue Mage: True Blue Update" id="ID_FFXIV_TRUE_BLUE_MAGE_MIMICRY_LABYRINTHINE_RECALL">
        <supports>Monster Mimicry Mythical</supports>
        <sheet display="false" />
    </element>
    <element name="Merfolks Blessing" type="Class Feature" source="The Blue Mage: True Blue Update" id="ID_FFXIV_TRUE_BLUE_MAGE_MIMICRY_MERFOLKS_BLESSING">
        <supports>Monster Mimicry Mythical</supports>
        <sheet display="false" />
    </element>
    <element name="Oil Spray" type="Class Feature" source="The Blue Mage: True Blue Update" id="ID_FFXIV_TRUE_BLUE_MAGE_MIMICRY_OIL_SPRAY">
        <supports>Monster Mimicry Mythical</supports>
        <sheet display="false" />
    </element>
    <element name="Oxidizing Touch" type="Class Feature" source="The Blue Mage: True Blue Update" id="ID_FFXIV_TRUE_BLUE_MAGE_MIMICRY_OXIDIZING_TOUCH">
        <supports>Monster Mimicry Mythical</supports>
        <sheet display="false" />
    </element>
    <element name="Psychometry" type="Class Feature" source="The Blue Mage: True Blue Update" id="ID_FFXIV_TRUE_BLUE_MAGE_MIMICRY_PSYCHOMETRY">
        <supports>Monster Mimicry Mythical</supports>
        <sheet display="false" />
    </element>
    <element name="Repulsive Breath" type="Class Feature" source="The Blue Mage: True Blue Update" id="ID_FFXIV_TRUE_BLUE_MAGE_MIMICRY_REPULSIVE_BREATH">
        <supports>Monster Mimicry Mythical</supports>
        <sheet display="false" />
    </element>
    <element name="Serpent Hair" type="Class Feature" source="The Blue Mage: True Blue Update" id="ID_FFXIV_TRUE_BLUE_MAGE_MIMICRY_SERPENT_HAIR">
        <supports>Monster Mimicry Mythical</supports>
        <sheet display="false" />
    </element>
    <element name="Shape-Shift" type="Class Feature" source="The Blue Mage: True Blue Update" id="ID_FFXIV_TRUE_BLUE_MAGE_MIMICRY_SHAPE_SHIFT">
        <supports>Monster Mimicry Mythical</supports>
        <sheet display="false" />
    </element>    
    <element name="Summon Mannequin" type="Class Feature" source="The Blue Mage: True Blue Update" id="ID_FFXIV_TRUE_BLUE_MAGE_MIMICRY_SUMMON_MANNEQUIN">
        <supports>Monster Mimicry Mythical</supports>
        <sheet display="false" />
    </element> 
    <element name="Temporal Flux" type="Class Feature" source="The Blue Mage: True Blue Update" id="ID_FFXIV_TRUE_BLUE_MAGE_MIMICRY_TEMPORAL_FLUX">
        <supports>Monster Mimicry Mythical</supports>
        <sheet display="false" />
    </element>
    <element name="Vanity Mirror" type="Class Feature" source="The Blue Mage: True Blue Update" id="ID_FFXIV_TRUE_BLUE_MAGE_MIMICRY_VANITY_MIRROR">
        <supports>Monster Mimicry Mythical</supports>
        <sheet display="false" />
    </element>
    <element name="Web of Hair" type="Class Feature" source="The Blue Mage: True Blue Update" id="ID_FFXIV_TRUE_BLUE_MAGE_MIMICRY_WEB_OF_HAIR">
        <supports>Monster Mimicry Mythical</supports>
        <sheet display="false" />
    </element>
    <element name="Azure Majora" type="Class Feature" source="The Blue Mage: True Blue Update" id="ID_FFXIV_TRUE_BLUE_MAGE_MIMICRY_AZURE_MAJORA">
        <supports>Monster Mimicry Mythical</supports>
        <requirements>[level:5]</requirements>
        <sheet display="false" />
    </element>
    <element name="Command Hair" type="Class Feature" source="The Blue Mage: True Blue Update" id="ID_FFXIV_TRUE_BLUE_MAGE_MIMICRY_COMMAND_HAIR">
        <supports>Monster Mimicry Mythical</supports>
        <requirements>[level:5]</requirements>
        <sheet display="false" />
    </element>   
    <element name="Consume Magic" type="Class Feature" source="The Blue Mage: True Blue Update" id="ID_FFXIV_TRUE_BLUE_MAGE_MIMICRY_CONSUME_MAGIC">
        <supports>Monster Mimicry Mythical</supports>
        <requirements>[level:5]</requirements>
        <sheet display="false" />
    </element>    
    <element name="Dimensional Rift" type="Class Feature" source="The Blue Mage: True Blue Update" id="ID_FFXIV_TRUE_BLUE_MAGE_DIMENSIONAL_RIFT">
        <supports>Monster Mimicry Mythical</supports>
        <requirements>[level:5]</requirements>
        <sheet display="false" />
    </element>
    <element name="Displacement" type="Class Feature" source="The Blue Mage: True Blue Update" id="ID_FFXIV_TRUE_BLUE_MAGE_MIMICRY_DISPLACEMENT">
        <supports>Monster Mimicry Mythical</supports>
        <requirements>[level:7]</requirements>
        <sheet display="false" />
    </element>    
    <element name="Dream Eater" type="Class Feature" source="The Blue Mage: True Blue Update" id="ID_FFXIV_TRUE_BLUE_MAGE_MIMICRY_DREAM_EATER">
        <supports>Monster Mimicry Mythical</supports>
        <requirements>[level:5]</requirements>
        <sheet display="false" />
    </element>
    <element name="Fey Charm" type="Class Feature" source="The Blue Mage: True Blue Update" id="ID_FFXIV_TRUE_BLUE_MAGE_MIMICRY_FEY_CHARM">
        <supports>Monster Mimicry Mythical</supports>
        <requirements>[level:7]</requirements>
        <sheet display="false" />
    </element>
    <element name="Implosion" type="Class Feature" source="The Blue Mage: True Blue Update" id="ID_FFXIV_TRUE_BLUE_MAGE_MIMICRY_IMPLOSION">
        <supports>Monster Mimicry Mythical</supports>
        <requirements>[level:5]</requirements>
        <sheet display="false" />
    </element>
    <element name="Insatiable Greed" type="Class Feature" source="The Blue Mage: True Blue Update" id="ID_FFXIV_TRUE_BLUE_MAGE_MIMICRY_INSATIABLE_GREED">
        <supports>Monster Mimicry Mythical</supports>
        <requirements>[level:5],ID_FFXIV_TRUE_BLUE_MAGE_MIMICRY_IRON_SCENT</requirements>
        <sheet display="false" />
    </element>
    <element name="Lilliputian Lyric" type="Class Feature" source="The Blue Mage: True Blue Update" id="ID_FFXIV_TRUE_BLUE_MAGE_MIMICRY_LILLIPUTIAN_LYRIC">
        <supports>Monster Mimicry Mythical</supports>
        <requirements>[level:5]</requirements>
        <sheet display="false" />
    </element>
    <element name="Malevolent Obsession" type="Class Feature" source="The Blue Mage: True Blue Update" id="ID_FFXIV_TRUE_BLUE_MAGE_MIMICRY_MALEVOLENT_POSSESSION">
        <supports>Monster Mimicry Mythical</supports>
        <requirements>[level:5]</requirements>
        <sheet display="false" />
    </element>
    <element name="Pocket Dimension" type="Class Feature" source="The Blue Mage: True Blue Update" id="ID_FFXIV_TRUE_BLUE_MAGE_MIMICRY_POCKET_DIMENSION">
        <supports>Monster Mimicry Mythical</supports>
        <requirements>[level:7]</requirements>
        <sheet display="false" />
    </element>
    <element name="Pond Chorus" type="Class Feature" source="The Blue Mage: True Blue Update" id="ID_FFXIV_TRUE_BLUE_MAGE_MIMICRY_POND_CHORUS">
        <supports>Monster Mimicry Mythical</supports>
        <requirements>[level:7]</requirements>
        <sheet display="false" />
    </element>
    <element name="Spell Vitalization" type="Class Feature" source="The Blue Mage: True Blue Update" id="ID_FFXIV_TRUE_BLUE_MAGE_MIMICRY_SPELL_VITALIZATION">
        <supports>Monster Mimicry Mythical</supports>
        <requirements>[level:7]</requirements>
        <sheet display="false" />
    </element>
    <element name="Time Slip" type="Class Feature" source="The Blue Mage: True Blue Update" id="ID_FFXIV_TRUE_BLUE_MAGE_MIMICRY_TIME_SLIP">
        <supports>Monster Mimicry Mythical</supports>
        <requirements>[level:7],ID_FFXIV_TRUE_BLUE_MAGE_MIMICRY_TEMPORAL_FLUX</requirements>
        <sheet display="false" />
    </element>
    <element name="Pixie Dust" type="Class Feature" source="The Blue Mage: True Blue Update" id="ID_FFXIV_TRUE_BLUE_MAGE_MIMICRY_PIXIE_DUST">
        <supports>Monster Mimicry Mythical</supports>
        <requirements>[level:11]</requirements>
        <sheet display="false" />
    </element>
    <!--Ancestral Lore-->
    <element name="Adaptive Camouflage" type="Class Feature" source="The Blue Mage: True Blue Update" id="ID_FFXIV_TRUE_BLUE_MAGE_MIMICRY_ADAPTIVE_CAMOUFLAGE">
        <supports>Monster Mimicry Ancestral</supports>
        <sheet display="false" />
    </element>
    <element name="Athletic Endurance" type="Class Feature" source="The Blue Mage: True Blue Update" id="ID_FFXIV_TRUE_BLUE_MAGE_MIMICRY_ATHLETIC_ENDURANCE">
        <supports>Monster Mimicry Ancestral</supports>
        <sheet display="false" />
    </element>
    <element name="Boon of the Postmaster" type="Class Feature" source="The Blue Mage: True Blue Update" id="ID_FFXIV_TRUE_BLUE_MAGE_MIMICRY_BOON_OF_THE_POSTMASTER">
        <supports>Monster Mimicry Ancestral</supports>
        <sheet display="false" />
    </element>
    <element name="Celerity" type="Class Feature" source="The Blue Mage: True Blue Update" id="ID_FFXIV_TRUE_BLUE_MAGE_MIMICRY_CELERITY">
        <supports>Monster Mimicry Ancestral</supports>
        <sheet display="false" />
    </element>
    <element name="Deadly Maul" type="Class Feature" source="The Blue Mage: True Blue Update" id="ID_FFXIV_TRUE_BLUE_MAGE_MIMICRY_DEADLY_MAUL">
        <supports>Monster Mimicry Ancestral</supports>
        <sheet display="false" />
    </element>
    <element name="Fledgling Wings" type="Class Feature" source="The Blue Mage: True Blue Update" id="ID_FFXIV_TRUE_BLUE_MAGE_MIMICRY_FLEDGLING_WINGS">
        <supports>Monster Mimicry Ancestral</supports>
        <sheet display="false" />
    </element>
    <element name="Hedge Wisdom" type="Class Feature" source="The Blue Mage: True Blue Update" id="ID_FFXIV_TRUE_BLUE_MAGE_MIMICRY_HEDGE_WISDOM">
        <supports>Monster Mimicry Ancestral</supports>
        <sheet display="false" />
    </element>
    <element name="Keen Senses" type="Class Feature" source="The Blue Mage: True Blue Update" id="ID_FFXIV_TRUE_BLUE_MAGE_MIMICRY_KEEN_SENSES">
        <supports>Monster Mimicry Ancestral</supports>
        <sheet display="false" />
    </element>
    <element name="Mighty Charge" type="Class Feature" source="The Blue Mage: True Blue Update" id="ID_FFXIV_TRUE_BLUE_MAGE_MIMICRY_MIGHTY_CHARGE">
        <supports>Monster Mimicry Ancestral</supports>
        <sheet display="false" />
    </element>
    <element name="Natural Projectiles" type="Class Feature" source="The Blue Mage: True Blue Update" id="ID_FFXIV_TRUE_BLUE_MAGE_MIMICRY_NATURAL_PROJECTILES">
        <supports>Monster Mimicry Ancestral</supports>
        <sheet display="false" />
    </element>
    <element name="Natures Gift" type="Class Feature" source="The Blue Mage: True Blue Update" id="ID_FFXIV_TRUE_BLUE_MAGE_MIMICRY_NATURES_GIFT">
        <supports>Monster Mimicry Ancestral</supports>
        <sheet display="false" />
    </element>
    <element name="Pack Formation" type="Class Feature" source="The Blue Mage: True Blue Update" id="ID_FFXIV_TRUE_BLUE_MAGE_MIMICRY_PACK_FORMATION">
        <supports>Monster Mimicry Ancestral</supports>
        <sheet display="false" />
    </element>
    <element name="Piercing Roar" type="Class Feature" source="The Blue Mage: True Blue Update" id="ID_FFXIV_TRUE_BLUE_MAGE_MIMICRY_PIERCING_ROAR">
        <supports>Monster Mimicry Ancestral</supports>
        <sheet display="false" />
    </element>
    <element name="Savage" type="Class Feature" source="The Blue Mage: True Blue Update" id="ID_FFXIV_TRUE_BLUE_MAGE_MIMICRY_SAVAGE">
        <supports>Monster Mimicry Ancestral</supports>
        <sheet display="false" />
    </element>
    <element name="Self Sacrifice" type="Class Feature" source="The Blue Mage: True Blue Update" id="ID_FFXIV_TRUE_BLUE_MAGE_MIMICRY_SELF_SACRIFICE">
        <supports>Monster Mimicry Ancestral</supports>
        <sheet display="false" />
    </element>
    <element name="Thermal Vision" type="Class Feature" source="The Blue Mage: True Blue Update" id="ID_FFXIV_TRUE_BLUE_MAGE_MIMICRY_THERMAL_VISION">
        <supports>Monster Mimicry Ancestral</supports>
        <sheet display="false" />
    </element>
    <element name="Tunneler" type="Class Feature" source="The Blue Mage: True Blue Update" id="ID_FFXIV_TRUE_BLUE_MAGE_MIMICRY_TUNNELER">
        <supports>Monster Mimicry Ancestral</supports>
        <sheet display="false" />
    </element>
    <element name="Web Sling" type="Class Feature" source="The Blue Mage: True Blue Update" id="ID_FFXIV_TRUE_BLUE_MAGE_MIMICRY_WEB_SLING">
        <supports>Monster Mimicry Ancestral</supports>
        <sheet display="false" />
    </element>
    <element name="Wing Attack" type="Class Feature" source="The Blue Mage: True Blue Update" id="ID_FFXIV_TRUE_BLUE_MAGE_MIMICRY_WING_ATTACK">
        <supports>Monster Mimicry Ancestral</supports>
        <sheet display="false" />
    </element>
    <element name="Inspiring Command: Forward" type="Class Feature" source="The Blue Mage: True Blue Update" id="ID_FFXIV_TRUE_BLUE_MAGE_MIMICRY_WOT_FORWARD">
        <supports>Monster Mimicry Ancestral</supports>
        <sheet display="false" />
    </element>
    <element name="Inspiring Command: Hold" type="Class Feature" source="The Blue Mage: True Blue Update" id="ID_FFXIV_TRUE_BLUE_MAGE_MIMICRY_WOT_HOLD">
        <supports>Monster Mimicry Ancestral</supports>
        <sheet display="false" />
    </element>
    <element name="Inspiring Command: Rally" type="Class Feature" source="The Blue Mage: True Blue Update" id="ID_FFXIV_TRUE_BLUE_MAGE_MIMICRY_WOT_RALLY">
        <supports>Monster Mimicry Ancestral</supports>
        <sheet display="false" />
    </element>
    <element name="Bastion Formation" type="Class Feature" source="The Blue Mage: True Blue Update" id="ID_FFXIV_TRUE_BLUE_MAGE_MIMICRY_BASTION_FORMATION">
        <supports>Monster Mimicry Ancestral</supports>
        <requirements>[level:5]</requirements>
        <sheet display="false" />
    </element> 
    <element name="Bestial Unity" type="Class Feature" source="The Blue Mage: True Blue Update" id="ID_FFXIV_TRUE_BLUE_MAGE_MIMICRY_BESTIAL_UNITY">
        <supports>Monster Mimicry Ancestral</supports>
        <requirements>[level:5]</requirements>
        <sheet display="false" />
    </element>
    <element name="Blinding Spores" type="Class Feature" source="The Blue Mage: True Blue Update" id="ID_FFXIV_TRUE_BLUE_MAGE_MIMICRY_BLINDING_SPORES">
        <supports>Monster Mimicry Ancestral</supports>
        <requirements>[level:5]</requirements>
        <sheet display="false" />
    </element>
    <element name="Booming Roar" type="Class Feature" source="The Blue Mage: True Blue Update" id="ID_FFXIV_TRUE_BLUE_MAGE_MIMICRY_BOOMING_ROAR">
        <supports>Monster Mimicry Ancestral</supports>
        <requirements>[level:5]</requirements>
        <sheet display="false" />
    </element>    
    <element name="Dreadful Resilience" type="Class Feature" source="The Blue Mage: True Blue Update" id="ID_FFXIV_TRUE_BLUE_MAGE_MIMICRY_DREADFUL_RESILIENCE">
        <supports>Monster Mimicry Ancestral</supports>
        <requirements>[level:5]</requirements>
        <sheet display="false" />
    </element>
    <element name="Engulf" type="Class Feature" source="The Blue Mage: True Blue Update" id="ID_FFXIV_TRUE_BLUE_MAGE_MIMICRY_ENGULF">
        <supports>Monster Mimicry Ancestral</supports>
        <requirements>[level:5]</requirements>
        <sheet display="false" />
    </element>
    <element name="Fearless Resolve" type="Class Feature" source="The Blue Mage: True Blue Update" id="ID_FFXIV_TRUE_BLUE_MAGE_MIMICRY_FEARLESS_RESOLVE">
        <supports>Monster Mimicry Ancestral</supports>
        <requirements>[level:5]</requirements>
        <sheet display="false" />
    </element>
    <element name="Green Blooded" type="Class Feature" source="The Blue Mage: True Blue Update" id="ID_FFXIV_TRUE_BLUE_MAGE_MIMICRY_GREEN_BLOODED">
        <supports>Monster Mimicry Ancestral</supports>
        <requirements>[level:5]</requirements>
        <sheet display="false" />
    </element>
    <element name="Heavy Spines" type="Class Feature" source="The Blue Mage: True Blue Update" id="ID_FFXIV_TRUE_BLUE_MAGE_MIMICRY_HEAVY_SPINES">
        <supports>Monster Mimicry Ancestral</supports>
        <requirements>[level:5],ID_FFXIV_TRUE_BLUE_MAGE_MIMICRY_NATURAL_PROJECTILES</requirements>
        <sheet display="false" />
    </element>
    <element name="Inspiring Command: Attack" type="Class Feature" source="The Blue Mage: True Blue Update" id="ID_FFXIV_TRUE_BLUE_MAGE_MIMICRY_WOT_ATTACK">
        <supports>Monster Mimicry Ancestral</supports>
        <requirements>[level:5]</requirements>
        <sheet display="false" />
    </element>
    <element name="Inspiring Command: Defend" type="Class Feature" source="The Blue Mage: True Blue Update" id="ID_FFXIV_TRUE_BLUE_MAGE_MIMICRY_WOT_DEFEND">
        <supports>Monster Mimicry Ancestral</supports>
        <requirements>[level:7]</requirements>
        <sheet display="false" />
    </element>
    <element name="Inspiring Command: Retreat" type="Class Feature" source="The Blue Mage: True Blue Update" id="ID_FFXIV_TRUE_BLUE_MAGE_MIMICRY_WOT_RETREAT">
        <supports>Monster Mimicry Ancestral</supports>
        <requirements>[level:7]</requirements>
        <sheet display="false" />
    </element>
    <element name="Invoke Rage" type="Class Feature" source="The Blue Mage: True Blue Update" id="ID_FFXIV_TRUE_BLUE_MAGE_MIMICRY_INVOKE_RAGE">
        <supports>Monster Mimicry Ancestral</supports>
        <requirements>[level:7]</requirements>
        <sheet display="false" />
    </element>
    <element name="Juvenile Wings" type="Class Feature" source="The Blue Mage: True Blue Update" id="ID_FFXIV_TRUE_BLUE_MAGE_MIMICRY_JUVENILE_WINGS">
        <supports>Monster Mimicry Ancestral</supports>
        <requirements>[level:5]</requirements>
        <sheet display="false" />
    </element>
    <element name="Mature Wings" type="Class Feature" source="The Blue Mage: True Blue Update" id="ID_FFXIV_TRUE_BLUE_MAGE_MIMICRY_MATURE_WINGS">
        <supports>Monster Mimicry Ancestral</supports>
        <requirements>[level:9],ID_FFXIV_TRUE_BLUE_MAGE_MIMICRY_JUVENILE_WINGS</requirements>
        <sheet display="false" />
    </element>
    <element name="Relentless Stalker" type="Class Feature" source="The Blue Mage: True Blue Update" id="ID_FFXIV_TRUE_BLUE_MAGE_MIMICRY_RELENTLESS_STALKER">
        <supports>Monster Mimicry Ancestral</supports>
        <requirements>[level:7]</requirements>
        <sheet display="false" />
    </element>
    <element name="Venomous Beast" type="Class Feature" source="The Blue Mage: True Blue Update" id="ID_FFXIV_TRUE_BLUE_MAGE_MIMICRY_VENOMOUS_BEAST">
        <supports>Monster Mimicry Ancestral</supports>
        <requirements>[level:7],(ID_FFXIV_TRUE_BLUE_MAGE_MIMICRY_NATURES_GIFT|ID_FFXIV_TRUE_BLUE_MAGE_MIMICRY_NATURAL_PROJECTILES)</requirements>
        <sheet display="false" />
    </element>
    <element name="Web Flurry" type="Class Feature" source="The Blue Mage: True Blue Update" id="ID_FFXIV_TRUE_BLUE_MAGE_MIMICRY_WEB_FLURRY">
        <supports>Monster Mimicry Ancestral</supports>
        <requirements>[level:5],ID_FFXIV_TRUE_BLUE_MAGE_MIMICRY_WEB_SLING</requirements>
        <sheet display="false" />
    </element>
    <element name="Wounded Fury" type="Class Feature" source="The Blue Mage: True Blue Update" id="ID_FFXIV_TRUE_BLUE_MAGE_MIMICRY_WOUNDED_FURY">
        <supports>Monster Mimicry Ancestral</supports>
        <requirements>[level:5]</requirements>
        <sheet display="false" />
    </element>
    <!--Primordial Lore-->
    <element name="Breath Weapon (Lesser)" type="Class Feature" source="The Blue Mage: True Blue Update" id="ID_FFXIV_TRUE_BLUE_MAGE_MIMICRY_BREATH_WEAPON_LESSER">
        <supports>Monster Mimicry Primordial</supports>
        <sheet display="false" />
    </element>
    <element name="Chromatic Lens" type="Class Feature" source="The Blue Mage: True Blue Update" id="ID_FFXIV_TRUE_BLUE_MAGE_MIMICRY_CHROMATIC_LENS">
        <supports>Monster Mimicry Primordial</supports>
        <sheet display="false" />
    </element>
    <element name="Dracolore" type="Class Feature" source="The Blue Mage: True Blue Update" id="ID_FFXIV_TRUE_BLUE_MAGE_MIMICRY_DRACOLORE">
        <supports>Monster Mimicry Primordial</supports>
        <sheet display="false" />
    </element>
    <element name="Energy Absorption" type="Class Feature" source="The Blue Mage: True Blue Update" id="ID_FFXIV_TRUE_BLUE_MAGE_MIMICRY_ENERGY_ABSORPTION">
        <supports>Monster Mimicry Primordial</supports>
        <sheet display="false" />
    </element>
    <element name="Flaming Leap" type="Class Feature" source="The Blue Mage: True Blue Update" id="ID_FFXIV_TRUE_BLUE_MAGE_MIMICRY_FLAMING_LEAP">
        <supports>Monster Mimicry Primordial</supports>
        <sheet display="false" />
    </element>
    <element name="Frigid Shield" type="Class Feature" source="The Blue Mage: True Blue Update" id="ID_FFXIV_TRUE_BLUE_MAGE_MIMICRY_FRIGID_SHIELD">
        <supports>Monster Mimicry Primordial</supports>
        <sheet display="false" />
    </element>
    <element name="Heart of the Dragon" type="Class Feature" source="The Blue Mage: True Blue Update" id="ID_FFXIV_TRUE_BLUE_MAGE_MIMICRY_HEART_OF_THE_DRAGON">
        <supports>Monster Mimicry Primordial</supports>
        <sheet display="false" />
    </element>
    <element name="Hide of the Ancients" type="Class Feature" source="The Blue Mage: True Blue Update" id="ID_FFXIV_TRUE_BLUE_MAGE_MIMICRY_HIDE_OF_THE_ANCIENTS">
        <supports>Monster Mimicry Primordial</supports>
        <sheet display="false" />
    </element>
    <element name="Ice Skate" type="Class Feature" source="The Blue Mage: True Blue Update" id="ID_FFXIV_TRUE_BLUE_MAGE_MIMICRY_ICE_SKATE">
        <supports>Monster Mimicry Primordial</supports>
        <sheet display="false" />
    </element>
    <element name="Lightning Backlash" type="Class Feature" source="The Blue Mage: True Blue Update" id="ID_FFXIV_TRUE_BLUE_MAGE_MIMICRY_LIGHTNING_BACKLASH">
        <supports>Monster Mimicry Primordial</supports>
        <sheet display="false" />
    </element>
    <element name="Mud Breath" type="Class Feature" source="The Blue Mage: True Blue Update" id="ID_FFXIV_TRUE_BLUE_MAGE_MIMICRY_MUD_BREATH">
        <supports>Monster Mimicry Primordial</supports>
        <sheet display="false" />
    </element>
    <element name="Olach Morrah" type="Class Feature" source="The Blue Mage: True Blue Update" id="ID_FFXIV_TRUE_BLUE_MAGE_MIMICRY_OLACH_MORRAH">
        <supports>Monster Mimicry Primordial</supports>
        <sheet display="false" />
    </element>
    <element name="Primal Erudition" type="Class Feature" source="The Blue Mage: True Blue Update" id="ID_FFXIV_TRUE_BLUE_MAGE_MIMICRY_PRIMAL_ERUDITION">
        <supports>Monster Mimicry Primordial</supports>
        <sheet display="false" />
    </element>
    <element name="Secrets of the Hordekeeper" type="Class Feature" source="The Blue Mage: True Blue Update" id="ID_FFXIV_TRUE_BLUE_MAGE_MIMICRY_SECRETS_OF_THE_HORDEKEEPER">
        <supports>Monster Mimicry Primordial</supports>
        <sheet display="false" />
    </element>
    <element name="Snowshoe" type="Class Feature" source="The Blue Mage: True Blue Update" id="ID_FFXIV_TRUE_BLUE_MAGE_MIMICRY_SNOWSHOE">
        <supports>Monster Mimicry Primordial</supports>
        <sheet display="false" />
    </element>
    <element name="Sonic Scream" type="Class Feature" source="The Blue Mage: True Blue Update" id="ID_FFXIV_TRUE_BLUE_MAGE_MIMICRY_SONIC_SCREAM">
        <supports>Monster Mimicry Primordial</supports>
        <sheet display="false" />
    </element>
    <!--Sacred Lore-->
    <element name="Discern Honesty" type="Class Feature" source="The Blue Mage: True Blue Update" id="ID_FFXIV_TRUE_BLUE_MAGE_MIMICRY_DISCERN_HONESTY">
        <supports>Monster Mimicry Sacred</supports>
        <sheet display="false" />
    </element>    
    <element name="Divine Will" type="Class Feature" source="The Blue Mage: True Blue Update" id="ID_FFXIV_TRUE_BLUE_MAGE_MIMICRY_DIVINE_WILL">
        <supports>Monster Mimicry Sacred</supports>
        <sheet display="false" />
    </element>
    <element name="Enlightenment" type="Class Feature" source="The Blue Mage: True Blue Update" id="ID_FFXIV_TRUE_BLUE_MAGE_MIMICRY_ENLIGHTENMENT">
        <supports>Monster Mimicry Sacred</supports>
        <sheet display="false" />
    </element>
    <element name="Glorious Light" type="Class Feature" source="The Blue Mage: True Blue Update" id="ID_FFXIV_TRUE_BLUE_MAGE_MIMICRY_GLORIOUS_LIGHT">
        <supports>Monster Mimicry Sacred</supports>
        <sheet display="false" />
    </element>
    <element name="Guiding Winds" type="Class Feature" source="The Blue Mage: True Blue Update" id="ID_FFXIV_TRUE_BLUE_MAGE_MIMICRY_GUIDING_WINDS">
        <supports>Monster Mimicry Sacred</supports>
        <sheet display="false" />
    </element>
    <element name="Phalanx Formation" type="Class Feature" source="The Blue Mage: True Blue Update" id="ID_FFXIV_TRUE_BLUE_MAGE_MIMICRY_PHALANX_FORMATION">
        <supports>Monster Mimicry Sacred</supports>
        <sheet display="false" />
    </element>
    <element name="Return to Nyx" type="Class Feature" source="The Blue Mage: True Blue Update" id="ID_FFXIV_TRUE_BLUE_MAGE_MIMICRY_RETURN_TO_NYX">
        <supports>Monster Mimicry Sacred</supports>
        <sheet display="false" />
    </element>
    <element name="Spiritual Sustenance" type="Class Feature" source="The Blue Mage: True Blue Update" id="ID_FFXIV_TRUE_BLUE_MAGE_MIMICRY_SPIRITUAL_SUSTENANCE">
        <supports>Monster Mimicry Sacred</supports>
        <sheet display="false" />
    </element>
    <!--Supernatural Lore-->
    <element name="Bite of the Kindred" type="Class Feature" source="The Blue Mage: True Blue Update" id="ID_FFXIV_TRUE_BLUE_MAGE_MIMICRY_BITE_OF_THE_KINDRED">
        <supports>Monster Mimicry Supernatural</supports>
        <sheet display="false" />
    </element>
    <element name="Bloodthirst" type="Class Feature" source="The Blue Mage: True Blue Update" id="ID_FFXIV_TRUE_BLUE_MAGE_MIMICRY_BLOODTHIRST">
        <supports>Monster Mimicry Supernatural</supports>
        <sheet display="false" />
    </element>
    <element name="Bottom Treader" type="Class Feature" source="The Blue Mage: True Blue Update" id="ID_FFXIV_TRUE_BLUE_MAGE_MIMICRY_BOTTOM_TREADER">
        <supports>Monster Mimicry Supernatural</supports>
        <sheet display="false" />
    </element>
    <element name="Cloak of Shadows" type="Class Feature" source="The Blue Mage: True Blue Update" id="ID_FFXIV_TRUE_BLUE_MAGE_MIMICRY_CLOAK_OF_SHADOWS">
        <supports>Monster Mimicry Supernatural</supports>
        <sheet display="false" />
    </element>
    <element name="Ghost Sight" type="Class Feature" source="The Blue Mage: True Blue Update" id="ID_FFXIV_TRUE_BLUE_MAGE_MIMICRY_GHOST_SIGHT">
        <supports>Monster Mimicry Supernatural</supports>
        <sheet display="false" />
    </element>
    <element name="Hellish Weapons" type="Class Feature" source="The Blue Mage: True Blue Update" id="ID_FFXIV_TRUE_BLUE_MAGE_MIMICRY_HELLISH_WEAPONS">
        <supports>Monster Mimicry Supernatural</supports>
        <sheet display="false" />
    </element>
    <element name="Maddening Feast" type="Class Feature" source="The Blue Mage: True Blue Update" id="ID_FFXIV_TRUE_BLUE_MAGE_MIMICRY_MADDENING_FEAST">
        <supports>Monster Mimicry Supernatural</supports>
        <sheet display="false" />
    </element>
    <element name="Pale Blessing" type="Class Feature" source="The Blue Mage: True Blue Update" id="ID_FFXIV_TRUE_BLUE_MAGE_MIMICRY_PALE_BLESSING">
        <supports>Monster Mimicry Supernatural</supports>
        <sheet display="false" />
    </element> 
    <element name="Pest Shapes" type="Class Feature" source="The Blue Mage: True Blue Update" id="ID_FFXIV_TRUE_BLUE_MAGE_MIMICRY_PEST_SHAPES">
        <supports>Monster Mimicry Supernatural</supports>
        <sheet display="false" />
    </element>
    <element name="Raxivorts Tongue" type="Class Feature" source="The Blue Mage: True Blue Update" id="ID_FFXIV_TRUE_BLUE_MAGE_MIMICRY_RAXIVORTS_TONGUE">
        <supports>Monster Mimicry Supernatural</supports>
        <sheet display="false" />
    </element>
    <element name="Shadow Blend" type="Class Feature" source="The Blue Mage: True Blue Update" id="ID_FFXIV_TRUE_BLUE_MAGE_MIMICRY_SHADOW_BLEND">
        <supports>Monster Mimicry Supernatural</supports>
        <sheet display="false" />
    </element>
    <element name="Shadow Dance" type="Class Feature" source="The Blue Mage: True Blue Update" id="ID_FFXIV_TRUE_BLUE_MAGE_MIMICRY_SHADOW_DANCE">
        <supports>Monster Mimicry Supernatural</supports>
        <sheet display="false" />
    <element name="Soul Weapon" type="Class Feature" source="The Blue Mage: True Blue Update" id="ID_FFXIV_TRUE_BLUE_MAGE_MIMICRY_SOUL_WEAPON">
    </element>
        <supports>Monster Mimicry Supernatural</supports>
        <sheet display="false" />
    </element>
    <element name="Swarm Shapes" type="Class Feature" source="The Blue Mage: True Blue Update" id="ID_FFXIV_TRUE_BLUE_MAGE_MIMICRY_SWARM_SHAPES">
        <supports>Monster Mimicry Supernatural</supports>
        <sheet display="false" />
    </element>
    <element name="Vermin Form" type="Class Feature" source="The Blue Mage: True Blue Update" id="ID_FFXIV_TRUE_BLUE_MAGE_MIMICRY_VERMIN_FORM">
        <supports>Monster Mimicry Supernatural</supports>
        <sheet display="false" />
    </element>
</elements>
    